{
  "lastUpdated": "2026-04-06",
  "palette": {
    "background": "#0a0b10",
    "surface": "#13151f",
    "surfaceAlt": "#1c1f2b",
    "primary": "#5e8bff",
    "primaryLight": "#8daaff",
    "secondary": "#ff5c7a",
    "accent": "#4de6b2",
    "accentWarm": "#ff9e57",
    "text": "#f2f5ff",
    "textMuted": "#c2c6d6",
    "textSubtle": "#a0a4b8",
    "border": "#2b2e3c",
    "glow": "rgba(94, 139, 255, 0.4)"
  },
  "typography": {
    "fontFamily": "Outfit",
    "codeFontFamily": "Fira Code",
    "headingWeight": "700",
    "bodyWeight": "400"
  },
  "aesthetic": {
    "style": "glassmorphism",
    "borderRadius": "16px",
    "cardBlur": "30px",
    "shadowIntensity": "medium",
    "animationSpeed": "0.5s",
    "glowRadius": "80px"
  },
  "gradient": {
    "hero": "linear-gradient(135deg, #5e8bff 0%, #4de6b2 50%, #ff9e57 100%)",
    "timeline": "linear-gradient(180deg, #13151f 0%, #5e8bff 50%, #ff9e57 100%)",
    "text": "linear-gradient(90deg, #5e8bff 0%, #4de6b2 50%, #ff5c7a 100%)"
  },
  "trendNote": "In April 2026, AI-themed websites are embracing a luminous, futuristic dark-mode design with a glassmorphism aesthetic, featuring vibrant gradients and soft glows. Typography trends focus on geometric sans-serif fonts like 'Outfit,' with animations that are smooth yet deliberate, evoking a sense of precision and innovation."
}
