{
  "lastUpdated": "2026-06-18",
  "palette": {
    "background": "#0a0c14",
    "surface": "#14171f",
    "surfaceAlt": "#1e2230",
    "primary": "#00b4d8",
    "primaryLight": "#60efff",
    "secondary": "#ff6f61",
    "accent": "#00d68f",
    "accentWarm": "#ffae42",
    "text": "#f0f4fc",
    "textMuted": "#b0b8cc",
    "textSubtle": "#8a92a5",
    "border": "#2a2f3d",
    "glow": "rgba(0, 180, 216, 0.3)"
  },
  "typography": {
    "fontFamily": "Inter",
    "codeFontFamily": "Fira Code",
    "headingWeight": "700",
    "bodyWeight": "400"
  },
  "aesthetic": {
    "style": "glassmorphism",
    "borderRadius": "16px",
    "cardBlur": "30px",
    "shadowIntensity": "medium",
    "animationSpeed": "0.5s",
    "glowRadius": "60px"
  },
  "gradient": {
    "hero": "linear-gradient(135deg, #00b4d8 0%, #60efff 50%, #ff6f61 100%)",
    "timeline": "linear-gradient(180deg, #14171f 0%, #00d68f 50%, #ffae42 100%)",
    "text": "linear-gradient(90deg, #60efff 0%, #00b4d8 50%, #ff6f61 100%)"
  },
  "trendNote": "In June 2026, dark-mode tech interfaces embrace vibrant neon accents and glassmorphism, combining depth with futuristic transparency. Smooth animations and high-contrast fonts reflect the season's energetic yet professional aesthetic, with gradients evoking a summery, high-tech vibe."
}
